doomarena/browsergym/__init__.py
doomarena/browsergym/attack_gateway.py
doomarena/browsergym/attack_scripts.py
doomarena/browsergym/attacked_browser_env_args.py
doomarena/browsergym/filters.py
doomarena/browsergym/init_scripts.py
doomarena/browsergym/success_filters.py
doomarena/browsergym/webarena_subsets.py
doomarena/browsergym/attacks/__init__.py
doomarena/browsergym/attacks/banner_attacks.py
doomarena/browsergym/attacks/div_injection.py
doomarena/browsergym/attacks/popup_attacks.py
doomarena/browsergym/attacks/user_generated_content.py
doomarena/browsergym/scripts/__init__.py
doomarena/browsergym/scripts/bgym_analysis.py
doomarena/browsergym/scripts/for_testing_run_demo_attack.py
doomarena/browsergym/scripts/run_banner_attack_webarena_reddit_notext.py
doomarena/browsergym/scripts/run_banner_with_alt_text_attack_webarena_reddit.py
doomarena/browsergym/scripts/run_bgym_experiment.py
doomarena/browsergym/scripts/run_parallel_bgym_experiment.py
doomarena/browsergym/scripts/run_popup_attack_webarena_reddit.py
doomarena/browsergym/scripts/sweep_bgym.py
doomarena/browsergym/scripts/test_task.py
doomarena/browsergym/scripts/automated_red_team/agent/__init__.py
doomarena/browsergym/scripts/automated_red_team/agent/main_prompt.py
doomarena/browsergym/scripts/automated_red_team/agent/red_team_agent.py
doomarena_browsergym-0.0.4.dist-info/METADATA
doomarena_browsergym-0.0.4.dist-info/WHEEL
doomarena_browsergym-0.0.4.dist-info/top_level.txt
doomarena_browsergym-0.0.4.dist-info/RECORD
