Metadata-Version: 2.4
Name: doomarena-browsergym
Version: 0.0.4
Summary: BrowserGym extensions for DoomArena
Author-email: Leo Boisvert <leo.boisvert@servicenow.com>, Abhay Puri <abhay.puri@servicenow.com>, Gabriel Huang <gabriel.huang@servicenow.com>, Mihir Bansal <mihir.bansal@servicenow.com>, Chandra Kiran Reddy Evuru <chandrakiranreddy.evuru@servicenow.com>, Avinandan Bose <avibose@uw.edu>, Maryam Fazel <mfazel@uw.edu>, Quentin Cappart <quentin.cappart@polymtl.ca>, Alexandre Lacoste <alexandre.lacoste@servicenow.com>, Alexandre Drouin <alexandre.drouin@servicenow.com>, Krishnamurthy DJ Dvijotham <d
Maintainer-email: Gabriel Huang <gabriel.huang@servicenow.com>, Leo Boisvert <leo.boisvert@servicenow.com>
License: Apache-2.0
Requires-Python: >=3.10
Requires-Dist: doomarena>=0.0.4
Requires-Dist: playwright
Requires-Dist: browsergym
Requires-Dist: agentlab
